pylettes/__init__.py
pylettes/base.py
pylettes/catpuccino/__init__.py
pylettes/catpuccino/frappe.py
pylettes/catpuccino/latte.py
pylettes/catpuccino/macchiato.py
pylettes/catpuccino/mocha.py
pylettes/dracula/__init__.py
pylettes/dracula/dracula.py
pylettes/hypersubatomic/__init__.py
pylettes/hypersubatomic/hypersubatomic.py
pylettes/monokai/__init__.py
pylettes/monokai/classic.py
pylettes/monokai/machine.py
pylettes/monokai/octagon.py
pylettes/monokai/pro.py
pylettes/monokai/ristretto.py
pylettes/monokai/spectrum.py
pylettes/one_dark/__init__.py
pylettes/one_dark/one_dark.py
pylettes/tokyo_night/__init__.py
pylettes/tokyo_night/tokyo_night.py
pylettes/tokyo_night/tokyo_night_light.py
pylettes/tokyo_night/tokyo_night_storm.py
vscode_pylettes-0.1.0.dist-info/LICENSE
vscode_pylettes-0.1.0.dist-info/METADATA
vscode_pylettes-0.1.0.dist-info/WHEEL
vscode_pylettes-0.1.0.dist-info/top_level.txt
vscode_pylettes-0.1.0.dist-info/RECORD
